trollduction/__init__.py
trollduction/custom_handler.py
trollduction/helper_functions.py
trollduction/producer.py
trollduction/producer_orig.py
trollduction/producer_orig_2.py
trollduction/producer_trimmed.py
trollduction/producer_trimmed_2.py
trollduction/version.py
trollduction/xml_read.py
trollduction-1.3.1.data/scripts/l2processor.py
trollduction-1.3.1.dist-info/DESCRIPTION.rst
trollduction-1.3.1.dist-info/METADATA
trollduction-1.3.1.dist-info/RECORD
trollduction-1.3.1.dist-info/WHEEL
trollduction-1.3.1.dist-info/metadata.json
trollduction-1.3.1.dist-info/top_level.txt
