Metadata-Version: 2.0
Name: trollduction
Version: 1.3.1
Summary: Pytroll batch production library
Home-page: https://github.com/pytroll/trollduction
Author: Martin Raspaud
Author-email: martin.raspaud@smhi.se
License: UNKNOWN
Platform: UNKNOWN
Classifier: Development Status :: 3 - Alpha
Classifier: Intended Audience :: Science/Research
Classifier: License :: OSI Approved :: GNU General Public License v3 or later (GPLv3+)
Classifier: Operating System :: OS Independent
Classifier: Programming Language :: Python
Classifier: Topic :: Scientific/Engineering
Requires-Dist: mpop
Requires-Dist: posttroll
Requires-Dist: pyresample
Requires-Dist: pykdtree
Requires-Dist: trollimage
Requires-Dist: pyorbital
Requires-Dist: trollsift
Requires-Dist: netifaces
Requires-Dist: pytroll-schedule
Requires-Dist: netcdf4
Requires-Dist: pytroll-collectors
